kernax/__init__.py
kernax/bjsamplers.py
kernax/discrepancies.py
kernax/kernels.py
kernax/quantization.py
kernax/thinning.py
kernax/types.py
kernax/utils.py
kernax-0.3.0.dist-info/WHEEL
kernax-0.3.0.dist-info/METADATA
kernax-0.3.0.dist-info/RECORD
