Metadata-Version: 2.3
Name: kernax
Version: 0.3.0
Summary: Regularized Stein thinning using JAX
Requires-Dist: blackjax>=1.2.5,<2.0.0
Requires-Dist: equinox>=0.13.0
Requires-Dist: jax>=0.6.2,<1.0.0
Requires-Dist: numpy>=2.2.6,<3.0.0
Requires-Dist: scipy>=1.15.3,<2.0.0
Requires-Dist: tqdm>=4.67.1
Requires-Dist: matplotlib>=3.10.5 ; extra == 'plot'
Requires-Dist: plotly>=6.3.0 ; extra == 'plot'
Requires-Python: >=3.10, <3.13
Provides-Extra: plot
